QuantumJobClient/__init__.py
QuantumJobClient/client.py
QuantumJobClient-0.0.4.1.dist-info/METADATA
QuantumJobClient-0.0.4.1.dist-info/WHEEL
QuantumJobClient-0.0.4.1.dist-info/entry_points.txt
QuantumJobClient-0.0.4.1.dist-info/top_level.txt
QuantumJobClient-0.0.4.1.dist-info/RECORD
