Metadata-Version: 2.2
Name: QuantumJobClient
Version: 0.0.4.1
Summary: A Python client library for interacting with quantum job details
Author: saipranay
Author-email: saipranay57@gmail.com
Classifier: Programming Language :: Python :: 3
Classifier: License :: OSI Approved :: MIT License
Classifier: Operating System :: OS Independent
Requires-Python: >=3.7
Requires-Dist: pymongo
Requires-Dist: python-dotenv
Requires-Dist: requests
Dynamic: author
Dynamic: author-email
Dynamic: classifier
Dynamic: requires-dist
Dynamic: requires-python
Dynamic: summary
